xwire/rest/__init__.py
xwire/rest/_private/__init__.py
xwire/rest/_private/proxy/__init__.py
xwire/rest/_private/proxy/decorators/__init__.py
xwire/rest/_private/proxy/decorators/cookies.py
xwire/rest/_private/proxy/decorators/get.py
xwire/rest/_private/proxy/decorators/headers.py
xwire/rest/_private/proxy/decorators/post.py
xwire/rest/_private/proxy/decorators/resource.py
xwire/rest/_private/utils.py
xwire/rest/public/__init__.py
xwire/rest/public/proxy.py
xwire.rest-0.1.14.dist-info/WHEEL
xwire.rest-0.1.14.dist-info/METADATA
xwire.rest-0.1.14.dist-info/RECORD
