Metadata-Version: 2.1
Name: xwire.rest
Version: 0.1.14
Summary: 
Author: tylerlaberge
Author-email: tylerlaberge@protonmail.com
Requires-Python: >=3.8,<4.0
Classifier: Programming Language :: Python :: 3
Classifier: Programming Language :: Python :: 3.8
Classifier: Programming Language :: Python :: 3.9
Requires-Dist: pytest-mock (>=3.5.1,<4.0.0)
Requires-Dist: requests (>=2.25.1,<3.0.0)
Requires-Dist: xwire.common (>=0.1.1,<0.2.0)
Requires-Dist: xwire.transport (>=0.1.9,<0.2.0)
